mobile_audio_kit/__init__.py
mobile_audio_kit/main.py
mobile_audio_kit/core/__init__.py
mobile_audio_kit/core/album.py
mobile_audio_kit/core/handlers.py
mobile_audio_kit/core/track.py
mobile_audio_kit/ui/__init__.py
mobile_audio_kit/ui/app.py
mobile_audio_kit-1.0.0.dist-info/METADATA
mobile_audio_kit-1.0.0.dist-info/WHEEL
mobile_audio_kit-1.0.0.dist-info/entry_points.txt
mobile_audio_kit-1.0.0.dist-info/licenses/LICENSE
mobile_audio_kit-1.0.0.dist-info/RECORD
