Metadata-Version: 2.4
Name: mobile-audio-kit
Version: 1.0.0
Summary: A terminal utility for managing audio file metadata
Project-URL: Homepage, https://github.com/llaisdy/mak
Project-URL: Bug Tracker, https://github.com/llaisdy/mak/issues
Author-email: Ivan Uemlianin <ivan@llaisdy.co.uk>
License: MIT License
License-File: LICENSE
Keywords: audio,metadata,music,terminal,tui
Classifier: Development Status :: 4 - Beta
Classifier: Environment :: Console
Classifier: Intended Audience :: End Users/Desktop
Classifier: License :: OSI Approved :: MIT License
Classifier: Programming Language :: Python :: 3
Classifier: Programming Language :: Python :: 3.8
Classifier: Programming Language :: Python :: 3.9
Classifier: Programming Language :: Python :: 3.10
Classifier: Programming Language :: Python :: 3.11
Classifier: Programming Language :: Python :: 3.12
Classifier: Topic :: Multimedia :: Sound/Audio
Classifier: Topic :: Utilities
Requires-Python: <3.13,>=3.8
Requires-Dist: mutagen>=1.47.0
Requires-Dist: pillow>=11.2.1
Requires-Dist: textual>=3.2.0
Provides-Extra: dev
Requires-Dist: pytest>=8.3.5; extra == 'dev'
Requires-Dist: textual-dev>=1.7.0; extra == 'dev'
